[{"container-title":"Physical Review E","author":[{"given":"Ira R.","family":"Cooke"},{"given":"Kurt","family":"Kremer"},{"given":"Markus","family":"Deserno"}],"DOI":"10.1103/physreve.72.011506","type":"article-journal","id":"Cooke_2005","citation-key":"Cooke_2005","ISSN":"1550-2376","issue":"1","issued":{"date-parts":[[2005,7]]},"publisher":"American Physical Society (APS)","title":"Tunable generic model for fluid bilayer membranes","URL":"http://dx.doi.org/10.1103/PhysRevE.72.011506","volume":"72","_graph":[{"type":"@biblatex/text","data":" @article{Cooke_2005, title={Tunable generic model for fluid bilayer membranes}, volume={72}, ISSN={1550-2376}, url={http://dx.doi.org/10.1103/PhysRevE.72.011506}, DOI={10.1103/physreve.72.011506}, number={1}, journal={Physical Review E}, publisher={American Physical Society (APS)}, author={Cooke, Ira R. and Kremer, Kurt and Deserno, Markus}, year={2005}, month=jul }\n"},{"type":"@biblatex/entries+list"},{"type":"@csl/list+object"}]}]